iotile_support_con_nrf52832_3/__init__.py
iotile_support_con_nrf52832_3/nrf52832_controller.py
iotile_support_con_nrf52832_3-3.2.4.dist-info/METADATA
iotile_support_con_nrf52832_3-3.2.4.dist-info/WHEEL
iotile_support_con_nrf52832_3-3.2.4.dist-info/entry_points.txt
iotile_support_con_nrf52832_3-3.2.4.dist-info/top_level.txt
iotile_support_con_nrf52832_3-3.2.4.dist-info/RECORD
