Metadata-Version: 2.1
Name: iotile-support-con-nrf52832-3
Version: 3.2.4
Summary: UNKNOWN
Home-page: UNKNOWN
Author: Arch
Author-email: info@arch-iot.com
License: UNKNOWN
Platform: UNKNOWN
Requires-Dist: iotile-support-lib-controller-3 (==3.*,>=3.7.14)
